promptmage/__init__.py
promptmage/api.py
promptmage/cli.py
promptmage/exceptions.py
promptmage/frontend/__init__.py
promptmage/frontend/components/__init__.py
promptmage/frontend/components/dataset_page.py
promptmage/frontend/components/evaluation_page.py
promptmage/frontend/components/flow_page.py
promptmage/frontend/components/main_runner.py
promptmage/frontend/components/menu.py
promptmage/frontend/components/overview_page.py
promptmage/frontend/components/prompts_page.py
promptmage/frontend/components/runs_page.py
promptmage/frontend/components/step_runner.py
promptmage/frontend/components/styles.py
promptmage/frontend/components/theme.py
promptmage/frontend/frontend.py
promptmage/mage.py
promptmage/prompt.py
promptmage/remote.py
promptmage/result.py
promptmage/run.py
promptmage/run_data.py
promptmage/static/android-chrome-192x192.png
promptmage/static/android-chrome-512x512.png
promptmage/static/apple-touch-icon.png
promptmage/static/favicon-16x16.png
promptmage/static/favicon-32x32.png
promptmage/static/favicon.ico
promptmage/static/index.html
promptmage/static/promptmage-logo.png
promptmage/static/site.webmanifest
promptmage/step.py
promptmage/storage/__init__.py
promptmage/storage/data_store.py
promptmage/storage/file_backend.py
promptmage/storage/memory_backend.py
promptmage/storage/prompt_store.py
promptmage/storage/remote_data_backend.py
promptmage/storage/remote_prompt_backend.py
promptmage/storage/sqlite_backend.py
promptmage/storage/storage_backend.py
promptmage/storage/utils.py
promptmage/utils.py
promptmage-0.1.4.dist-info/LICENSE
promptmage-0.1.4.dist-info/METADATA
promptmage-0.1.4.dist-info/WHEEL
promptmage-0.1.4.dist-info/entry_points.txt
promptmage-0.1.4.dist-info/RECORD
