Metadata-Version: 2.1
Name: promptmage
Version: 0.1.4
Summary: "PromptMage" is designed to offer an intuitive interface that simplifies the process of creating and managing LLM workflows as a self-hosted solution.
Home-page: https://www.promptmage.io
License: MIT
Keywords: promptmage,llm,workflow,management,self-hosted,solution,ai,nlp,prompt
Author: Tobias Sterbak
Author-email: github@tobiassterbak.com
Requires-Python: >=3.11,<4.0
Classifier: License :: OSI Approved :: MIT License
Classifier: Programming Language :: Python :: 3
Classifier: Programming Language :: Python :: 3.11
Classifier: Programming Language :: Python :: 3.12
Classifier: Topic :: Scientific/Engineering :: Artificial Intelligence
Classifier: Topic :: Software Development :: Libraries :: Python Modules
Requires-Dist: click (>=8.1.7,<9.0.0)
Requires-Dist: fastapi (>=0.109.1,<0.110.0)
Requires-Dist: loguru (>=0.7.2,<0.8.0)
Requires-Dist: nicegui (>=1.4.25,<2.0.0)
Requires-Dist: python-slugify (>=8.0.4,<9.0.0)
Requires-Dist: setuptools (>=69.5.1,<70.0.0)
Requires-Dist: sqlalchemy (>=2.0.31,<3.0.0)
Requires-Dist: uvicorn[standard] (>=0.29.0,<0.30.0)
Requires-Dist: websockets (>=13.1,<14.0)
Project-URL: Repository, https://github.comm/tsterbak/promptmage
